myminapp/__init__.py
myminapp/app.py
myminapp/appdef.py
myminapp/appserver.py
myminapp/data/cert/placeholder
myminapp/data/cert/bosch/placeholder
myminapp/data/cert/ca/placeholder
myminapp/data/log/placeholder
myminapp/data/storage/placeholder
myminapp/data/storage/test_epstats.db
myminapp/data/temp/camera/placeholder
myminapp/data/temp/camera/test-numcam757-2.bmp
myminapp/data/temp/camera/test-numcam757.bmp
myminapp/data/temp/chart/placeholder
myminapp/data/temp/chart/test_epstats-energy-bar-chart.svg
myminapp/data/temp/chart/test_epstats-energy-line-chart.svg
myminapp/data/temp/chart/test_epstats-energy-pie-chart.svg
myminapp/data/temp/chart/test_epstats-power-bar-chart.svg
myminapp/data/temp/chart/test_epstats-power-line-chart.svg
myminapp/data/temp/chart/test_epstats-power-pie-chart.svg
myminapp/data/temp/chart/test_epstats-powerplus-bar-chart.svg
myminapp/data/temp/chart/test_epstats-powerplus-line-chart.svg
myminapp/data/temp/chart/test_epstats-powerplus-pie-chart.svg
myminapp/data/temp/textdoc/placeholder
myminapp/doc/LICENSE
myminapp/doc/myminapp-manual-de.pdf
myminapp/doc/myminapp-manual-en.pdf
myminapp/doc/image/logo.png
myminapp/doc/image/web.png
myminapp/lib/__init__.py
myminapp/lib/command/__init__.py
myminapp/lib/command/cmd.py
myminapp/lib/command/epstats.py
myminapp/lib/command/helloworld.py
myminapp/lib/command/monitorview.py
myminapp/lib/command/pscharge.py
myminapp/lib/command/psdischarge.py
myminapp/lib/command/selection.py
myminapp/lib/command/setting.py
myminapp/lib/command/state.py
myminapp/lib/command/textdoc.py
myminapp/lib/device/__init__.py
myminapp/lib/device/camera/__init__.py
myminapp/lib/device/camera/numcam757.py
myminapp/lib/device/graphic/__init__.py
myminapp/lib/device/graphic/chart.py
myminapp/lib/device/inverter/__init__.py
myminapp/lib/device/inverter/opendtu.py
myminapp/lib/device/meter/__init__.py
myminapp/lib/device/meter/dtsu.py
myminapp/lib/device/plug/__init__.py
myminapp/lib/device/plug/bosch.py
myminapp-0.9.4.dist-info/LICENSE
myminapp-0.9.4.dist-info/METADATA
myminapp-0.9.4.dist-info/WHEEL
myminapp-0.9.4.dist-info/top_level.txt
myminapp-0.9.4.dist-info/RECORD
