Metadata-Version: 2.1
Name: myminapp
Version: 0.9.4
Summary: A minimal but complete Python example application
Author: https://github.com/berryunit
License: myminapp
Project-URL: repository, https://github.com/berryunit/myminapp
Keywords: education,learning,practise,example,examples,sample,samples,smarthome,smart home,homeautomation,home automation,diy,modbus,fritz,bosch,shelly,opendtu,raspberry,relay
Classifier: Development Status :: 4 - Beta
Classifier: Operating System :: OS Independent
Classifier: License :: OSI Approved :: MIT License
Classifier: Programming Language :: Python :: 3
Requires-Python: >=3.10
License-File: LICENSE
Provides-Extra: device
Requires-Dist: requests ; extra == 'device'
Requires-Dist: fritzconnection ; extra == 'device'
Requires-Dist: minimalmodbus ; extra == 'device'
Requires-Dist: pygal ; extra == 'device'
Requires-Dist: pygame ; extra == 'device'
